LICENSE
README.md
setup.py
kmm4g/__init__.py
kmm4g/kmm4g.py
kmm4g.egg-info/PKG-INFO
kmm4g.egg-info/SOURCES.txt
kmm4g.egg-info/dependency_links.txt
kmm4g.egg-info/entry_points.txt
kmm4g.egg-info/requires.txt
kmm4g.egg-info/top_level.txt
kmm4g/mysql-cluster/Chart.yaml
kmm4g/mysql-cluster/values.yaml
kmm4g/mysql-cluster/templates/NodePort.yaml
kmm4g/mysql-cluster/templates/_helpers.tpl
kmm4g/mysql-cluster/templates/backup-secret.yaml
kmm4g/mysql-cluster/templates/cluster.yaml
kmm4g/mysql-cluster/templates/secret.yaml