Metadata-Version: 2.1
Name: kmm4g
Version: 1.0.6
Summary: Kubernetes MySQL Manager for GIG.tech based clouds.
Home-page: https://git.gig.tech/ateam-public/kmm4g
Author: Abdalluh Mostafa
Author-email: abdalluh.mostafa@whitesky.cloud
License: UNKNOWN
Keywords: kmm4g,kmm,Kubernetes,MySQL,Manager,GIG
Platform: UNKNOWN
Classifier: Programming Language :: Python :: 3.8
Classifier: Development Status :: 5 - Production/Stable
Classifier: Intended Audience :: Developers
Classifier: Topic :: Software Development :: Build Tools
Classifier: License :: OSI Approved :: MIT License
Classifier: Operating System :: OS Independent
Requires-Python: >=3.8
License-File: LICENSE
